ebaysdksearch/__init__.py
ebaysdksearch/ebaysearch.py
tests/__init__.py
tests/test_ebaysearch.py
ebaysdksearch-0.0.1.dist-info/METADATA
ebaysdksearch-0.0.1.dist-info/WHEEL
ebaysdksearch-0.0.1.dist-info/top_level.txt
ebaysdksearch-0.0.1.dist-info/RECORD
