Metadata-Version: 2.1
Name: ebaysdksearch
Version: 0.0.1
Summary: common commodity plotting including seasonal charts using plotly
Home-page: https://github.com/aeorxc/ebaysdksearch
Author: aeorxc
Author-email: author@example.com
License: UNKNOWN
Project-URL: Source, https://github.com/aeorxc/ebaysdksearch
Platform: UNKNOWN
Classifier: Programming Language :: Python :: 3
Classifier: License :: OSI Approved :: MIT License
Classifier: Operating System :: OS Independent
Requires-Python: >=3.9
Requires-Dist: ebaysdk
Requires-Dist: requests
Requires-Dist: python-dotenv
Requires-Dist: cachetools
